{
    "第 1 場": {
        "個別馬匹因素": [
            {
                "馬號": "01",
                "馬名": "摘星聲升",
                "配備": "B-/CP1",
                "途程": "+450"
            },
            {
                "馬號": "03",
                "馬名": "川河型駒",
                "配備": "V-/B2",
                "評分": "-18"
            },
            {
                "馬號": "04",
                "馬名": "多利神駒",
                "配備": "CP-"
            },
            {
                "馬號": "05",
                "馬名": "駟跑得",
                "從化回港日期": "11/07/2026"
            },
            {
                "馬號": "08",
                "馬名": "悠悠乾坤",
                "從化回港日期": "09/07/2026"
            },
            {
                "馬號": "09",
                "馬名": "架勢奇爸",
                "途程": "-550"
            },
            {
                "馬號": "11",
                "馬名": "電訊驕陽",
                "途程": "-550"
            }
        ],
        "同廄馬匹摘要": []
    },
    "第 2 場": {
        "個別馬匹因素": [
            {
                "馬號": "02",
                "馬名": "紅錢到",
                "從化回港日期": "09/07/2026"
            },
            {
                "馬號": "03",
                "馬名": "好運多彩",
                "今賽口銜鐵": "RB",
                "從化回港日期": "07/07/2026"
            },
            {
                "馬號": "04",
                "馬名": "團結戰靈",
                "配備": "CP-/XB/V1"
            },
            {
                "馬號": "05",
                "馬名": "友聲友色",
                "上賽口銜鐵": "NB",
                "今賽口銜鐵": "RB",
                "上賽距今日數": "178",
                "從化回港日期": "05/02/2026"
            },
            {
                "馬號": "06",
                "馬名": "勝利君子",
                "配備": "SR-",
                "上賽距今日數": "207",
                "從化回港日期": "18/06/2026"
            },
            {
                "馬號": "07",
                "馬名": "三強",
                "配備": "P-"
            },
            {
                "馬號": "09",
                "馬名": "天下寵兒",
                "配備": "CP2",
                "從化回港日期": "04/07/2026"
            },
            {
                "馬號": "10",
                "馬名": "星威心得",
                "評分": "-20"
            },
            {
                "馬號": "12",
                "馬名": "精益大師",
                "評分": "-16"
            }
        ],
        "同廄馬匹摘要": []
    },
    "第 3 場": {
        "個別馬匹因素": [
            {
                "馬號": "01",
                "馬名": "香港神駒",
                "從化回港日期": "18/06/2026"
            },
            {
                "馬號": "04",
                "馬名": "浪漫老撾",
                "評分": "-20",
                "途程": "+400"
            },
            {
                "馬號": "05",
                "馬名": "八駿笑昇",
                "從化回港日期": "25/06/2026"
            },
            {
                "馬號": "07",
                "馬名": "勁步速",
                "配備": "CP-"
            },
            {
                "馬號": "09",
                "馬名": "大千氣象",
                "評分": "-20"
            },
            {
                "馬號": "10",
                "馬名": "家樂寶駒",
                "從化回港日期": "07/07/2026"
            },
            {
                "馬號": "11",
                "馬名": "北海盜",
                "評分": "-16",
                "從化回港日期": "11/07/2026"
            }
        ],
        "同廄馬匹摘要": []
    },
    "第 4 場": {
        "個別馬匹因素": [
            {
                "馬號": "01",
                "馬名": "深心星",
                "從化回港日期": "07/07/2026"
            },
            {
                "馬號": "02",
                "馬名": "大學生",
                "配備": "SR-/CP1"
            },
            {
                "馬號": "04",
                "馬名": "先到先得",
                "從化回港日期": "04/07/2026"
            },
            {
                "馬號": "05",
                "馬名": "凱皇寶",
                "從化回港日期": "04/06/2026"
            },
            {
                "馬號": "06",
                "馬名": "劍飛聲",
                "評分": "-18"
            },
            {
                "馬號": "09",
                "馬名": "瑞祺威楓",
                "配備": "E2",
                "評分": "-17"
            },
            {
                "馬號": "10",
                "馬名": "同心",
                "配備": "B-/XB/V1",
                "評分": "-18"
            },
            {
                "馬號": "11",
                "馬名": "傲然",
                "評分": "-22",
                "從化回港日期": "09/07/2026"
            }
        ],
        "同廄馬匹摘要": []
    },
    "第 5 場": {
        "個別馬匹因素": [
            {
                "馬號": "03",
                "馬名": "快樂神駒",
                "從化回港日期": "11/07/2026"
            },
            {
                "馬號": "04",
                "馬名": "笑必勝",
                "綁繫舌帶": "TT-",
                "上賽口銜鐵": "LB",
                "今賽口銜鐵": "RB",
                "上賽距今日數": "67"
            },
            {
                "馬號": "06",
                "馬名": "盛勢威楓",
                "途程": "-450",
                "上賽距今日數": "70",
                "從化回港日期": "09/07/2026"
            },
            {
                "馬號": "07",
                "馬名": "喜意",
                "從化回港日期": "11/07/2026"
            },
            {
                "馬號": "08",
                "馬名": "帶贏來",
                "綁繫舌帶": "TT1"
            },
            {
                "馬號": "10",
                "馬名": "威威神駒",
                "綁繫舌帶": "TT1"
            },
            {
                "馬號": "11",
                "馬名": "久久為軍",
                "評分": "-20"
            }
        ],
        "同廄馬匹摘要": []
    },
    "第 6 場": {
        "個別馬匹因素": [
            {
                "馬號": "04",
                "馬名": "合夥飛馳",
                "配備": "XB/V1",
                "從化回港日期": "18/06/2026"
            },
            {
                "馬號": "09",
                "馬名": "精彩勇將",
                "配備": "SR1"
            },
            {
                "馬號": "10",
                "馬名": "神異金剛",
                "評分": "-16"
            },
            {
                "馬號": "11",
                "馬名": "領袖勁力",
                "評分": "-21"
            },
            {
                "馬號": "12",
                "馬名": "閃電武士",
                "從化回港日期": "27/06/2026"
            }
        ],
        "同廄馬匹摘要": []
    },
    "第 7 場": {
        "個別馬匹因素": [
            {
                "馬號": "01",
                "馬名": "又龍串鳳",
                "途程": "-350"
            },
            {
                "馬號": "03",
                "馬名": "有財有勢",
                "從化回港日期": "04/07/2026"
            },
            {
                "馬號": "04",
                "馬名": "傲視同群",
                "上賽距今日數": "210",
                "從化回港日期": "18/06/2026"
            },
            {
                "馬號": "05",
                "馬名": "我做到",
                "配備": "B-/H"
            },
            {
                "馬號": "06",
                "馬名": "勝兄弟",
                "配備": "B1"
            },
            {
                "馬號": "07",
                "馬名": "喜豐年",
                "配備": "SR-/XB",
                "上賽距今日數": "94"
            },
            {
                "馬號": "08",
                "馬名": "勁好運",
                "從化回港日期": "11/07/2026"
            },
            {
                "馬號": "10",
                "馬名": "棒棒糖",
                "配備": "PC-",
                "評分": "+17",
                "途程": "+450",
                "上賽距今日數": "63",
                "從化回港日期": "04/06/2026"
            },
            {
                "馬號": "12",
                "馬名": "摯友勝",
                "途程": "+450"
            }
        ],
        "同廄馬匹摘要": []
    },
    "第 8 場": {
        "個別馬匹因素": [
            {
                "馬號": "01",
                "馬名": "幸運有您",
                "從化回港日期": "09/07/2026",
                "同廄多駒出戰": "是"
            },
            {
                "馬號": "03",
                "馬名": "翠紅",
                "評分": "+23"
            },
            {
                "馬號": "05",
                "馬名": "維港智能",
                "評分": "-21"
            },
            {
                "馬號": "07",
                "馬名": "魔術控制",
                "配備": "V-",
                "評分": "-16"
            },
            {
                "馬號": "09",
                "馬名": "友愛心得",
                "評分": "+17"
            },
            {
                "馬號": "10",
                "馬名": "小霸王",
                "從化回港日期": "09/07/2026"
            },
            {
                "馬號": "11",
                "馬名": "興馳千里",
                "評分": "+32",
                "同廄多駒出戰": "是"
            }
        ],
        "同廄馬匹摘要": [
            {
                "練馬師": "羅富全",
                "馬號": "01, 02"
            },
            {
                "練馬師": "呂健威",
                "馬號": "08, 11"
            }
        ]
    },
    "第 9 場": {
        "個別馬匹因素": [
            {
                "馬號": "01",
                "馬名": "東來欣賞",
                "評分": "+26"
            },
            {
                "馬號": "02",
                "馬名": "競駿皇者",
                "配備": "B1"
            },
            {
                "馬號": "08",
                "馬名": "龍城精將",
                "途程": "-400"
            },
            {
                "馬號": "09",
                "馬名": "逍遙騎士",
                "途程": "-400"
            },
            {
                "馬號": "11",
                "馬名": "繼往開來",
                "從化回港日期": "04/07/2026"
            }
        ],
        "同廄馬匹摘要": []
    },
    "第 10 場": {
        "個別馬匹因素": [],
        "同廄馬匹摘要": []
    },
    "第 11 場": {
        "個別馬匹因素": [],
        "同廄馬匹摘要": []
    }
}